Metadata-Version: 2.4
Name: autopdex
Version: 1.1.4
Summary: An automized PDE solver for accelerators based on JAX
Author: Tobias Bode
License-Expression: AGPL-3.0-only
Classifier: Programming Language :: Python :: 3
Classifier: Operating System :: OS Independent
Requires-Python: >=3.10
License-File: LICENSE
Requires-Dist: flax>=0.8.1
Requires-Dist: jax>=0.4.26
Requires-Dist: jaxlib>=0.4.26
Requires-Dist: jaxopt>=0.8.3
Requires-Dist: meshio>=5.3.5
Requires-Dist: numpy>=1.26.4
Requires-Dist: plotly>=5.15.0
Requires-Dist: pygmsh>=7.1.17
Requires-Dist: pyvista>=0.43.3
Requires-Dist: scipy>=1.13.0
Requires-Dist: scikit-optimize>=0.9.0
Requires-Dist: pytest>=8.3.2
Provides-Extra: dev
Requires-Dist: equinox; extra == "dev"
Requires-Dist: pyamg; extra == "dev"
Requires-Dist: pypardiso; extra == "dev"
Requires-Dist: petsc4py; extra == "dev"
Requires-Dist: sparse_dot_mkl; extra == "dev"
Dynamic: license-file
